{
    "name": "Torben Van Assche",
    "birthDate": "1995-11-21",
    "pictureURL": "assets/sprites/photo-zoomed.jpg",
    "chibiURL": "assets/sprites/chibi.png",
    "synopsis": [
        "Lorem ipsum dolor sit amet, consectetur adipiscing elit. Nulla elementum, enim sodales egestas fermentum, augue eros dictum lectus, nec finibus mi ligula sit amet erat. Integer in ullamcorper neque. Praesent pulvinar aliquam vehicula. Nam egestas justo ex, in tempor dui elementum a. Suspendisse euismod auctor nulla, et sollicitudin orci hendrerit a. Fusce in augue magna. Sed vestibulum tortor sed lorem tincidunt, id finibus enim finibus.Nunc laoreet interdum dui a sodales. Integer luctus, ante a blandit efficitur, diam lacus consectetur nulla, id mollis arcu sapien ut dui.",
        "Curabitur porta facilisis lectus vitae sodales. Nullam consectetur, nisi id interdum feugiat, ante dui vehicula nibh, non euismod arcu felis id nisl. Suspendisse id interdum purus. In at mi non massa fringilla consectetur. Etiam sed enim ultricies, aliquam dui quis, luctus lacus. Nam tempus tortor tellus, sit amet rutrum tortor tincidunt nec. Duis rhoncus, diam quis facilisis dictum, massa eros placerat diam, imperdiet tempor ante risus quis nisi. Nunc eget lectus imperdiet, cursus metus ut, pretium velit. Nullam imperdiet viverra commodo. Phasellus congue dictum leo id congue. Sed dignissim diam sed auctor elementum. Morbi gravida, quam a ornare euismod, urna nunc malesuada lorem, quis faucibus ipsum enim et lacus.",
        "Lorem ipsum dolor sit amet, consectetur adipiscing elit. Nulla elementum, enim sodales egestas fermentum, augue eros dictum lectus, nec finibus mi ligula sit amet erat. Integer in ullamcorper neque. Praesent pulvinar aliquam vehicula. Nam egestas justo ex, in tempor dui elementum a. Suspendisse euismod auctor nulla, et sollicitudin orci hendrerit a. Fusce in augue magna. Sed vestibulum tortor sed lorem tincidunt, id finibus enim finibus."
    ],
    "competences": [
        {
            "name": "Unity",
            "amount": 90,
            "color": "#111111"
        },
        {
            "name": "C++",
            "amount": 30,
            "color": "#111111"
        },
        {
            "name": "C#",
            "amount": 65,
            "color": "#111111"
        },
        {
            "name": "Web",
            "amount": 50,
            "color": "#111111"
        },
        {
            "name": "Angular",
            "amount": 40,
            "color": "#111111"
        },
        {
            "name": "3D",
            "amount": 50,
            "color": "#111111"
        },
        {
            "name": "Rigging",
            "amount": 65,
            "color": "#111111"
        },
        {
            "name": "Python",
            "amount": 25,
            "color": "#111111"
        }
    ],
    "contact": [
        {
            "link": "https://github.com/GrimZero",
            "img": "assets/svg/contact/github.svg"
        },
        {
            "link": "https://www.facebook.com/torben.vanassche.3",
            "img": "assets/svg/contact/facebook.svg"
        },
        {
            "link": "https://www.linkedin.com/in/torben-van-assche-931982153/",
            "img": "assets/svg/contact/linkedin.svg"
        },
        {
            "link": "https://discordapp.com/channels/@me/Protagonist-kun#5509/",
            "img": "assets/svg/contact/discord.svg"
        },
        {
            "link": "mailto:torbenvanassche.dev@gmail.com",
            "img": "assets/svg/contact/envelope.svg"
        }
    ]
}